postalcodes_ca/__init__.py
postalcodes_ca/import.py
postalcodes_ca/postalcodes.db
postalcodes_ca/settings.py
postalcodes_ca-0.0.8.dist-info/METADATA
postalcodes_ca-0.0.8.dist-info/WHEEL
postalcodes_ca-0.0.8.dist-info/top_level.txt
postalcodes_ca-0.0.8.dist-info/RECORD
