Metadata-Version: 2.1
Name: postalcodes-ca
Version: 0.0.8
Summary: Radius searches on Canadian FSA codes, location data
Home-page: https://github.com/verhovsky/postalcodes-ca
Author: Boris Verkhovskiy
Author-email: boris.verk@gmail.com
License: MIT
Keywords: Canada,postal,code,distance,geonames
Platform: UNKNOWN
Classifier: Development Status :: 4 - Beta
Classifier: License :: OSI Approved :: MIT License
Classifier: Operating System :: MacOS :: MacOS X
Classifier: Operating System :: POSIX
Classifier: Operating System :: Microsoft :: Windows
Classifier: Programming Language :: Python :: 3
Classifier: Programming Language :: Python :: 3 :: Only
Classifier: Programming Language :: Python :: 3.7
Classifier: Programming Language :: Python :: 3.8
Classifier: Programming Language :: Python :: 3.9
Classifier: Programming Language :: Python :: Implementation :: CPython
Requires-Python: >=3.7
